django_index_optimizer-0.1.0.dist-info/licenses/LICENSE
optimizer/__init__.py
optimizer/analyzer.py
optimizer/applier.py
optimizer/apps.py
optimizer/recommender.py
optimizer/management/__init__.py
optimizer/management/commands/__init__.py
optimizer/management/commands/optimize_indexes.py
django_index_optimizer-0.1.0.dist-info/METADATA
django_index_optimizer-0.1.0.dist-info/WHEEL
django_index_optimizer-0.1.0.dist-info/top_level.txt
django_index_optimizer-0.1.0.dist-info/RECORD
