Metadata-Version: 2.4
Name: django-index-optimizer
Version: 0.1.0
Summary: A Django app that analyzes PostgreSQL query performance and recommends indexes.
Author-email: Your Name <your@email.com>
License: MIT
Requires-Python: >=3.8
License-File: LICENSE
Requires-Dist: Django>=3.2
Dynamic: license-file
